README.md
setup.cfg
setup.py
theorem10/__init__.py
theorem10.egg-info/PKG-INFO
theorem10.egg-info/SOURCES.txt
theorem10.egg-info/dependency_links.txt
theorem10.egg-info/top_level.txt