Metadata-Version: 2.1
Name: theorem10
Version: 1.1
Summary: This repository includes a computer program for a mathematical theorem paper titled A theorem on numbers of the form 10^x
Home-page: https://github.com/mr-ravin/theorem10
Author: Ravin Kumar
Author-email: mr.ravin_kumar@hotmail.com
License: UNKNOWN
Platform: UNKNOWN
Classifier: Programming Language :: Python :: 3
Classifier: License :: OSI Approved :: GNU General Public License (GPL)
Classifier: Operating System :: OS Independent
